ocvproto/__init__.py
ocvproto/backend.py
ocvproto/exceptions.py
ocvproto/frame.py
ocvproto/toolbox.py
ocvproto/app/__init__.py
ocvproto/app/application.py
ocvproto/app/config.py
ocvproto/app/keys.py
ocvproto/misc/__init__.py
ocvproto/misc/canvas.py
ocvproto/misc/colors.py
ocvproto/misc/text.py
ocvproto/primitives/__init__.py
ocvproto/primitives/legend.py
ocvproto/sources/__init__.py
ocvproto/sources/base.py
ocvproto/sources/camera.py
ocvproto/sources/image.py
ocvproto/sources/video.py
ocvproto/ui/__init__.py
ocvproto/ui/window.py
ocvproto/ui/wm.py
ocvproto/ui/trackbars/__init__.py
ocvproto/ui/trackbars/base.py
opencv_proto-0.3.0.dist-info/AUTHORS
opencv_proto-0.3.0.dist-info/LICENSE
opencv_proto-0.3.0.dist-info/METADATA
opencv_proto-0.3.0.dist-info/WHEEL
opencv_proto-0.3.0.dist-info/top_level.txt
opencv_proto-0.3.0.dist-info/RECORD
