Metadata-Version: 2.1
Name: opencv-proto
Version: 0.3.0
Summary: Allows fast prototyping in Python for OpenCV
Home-page: https://github.com/idlesign/opencv-proto
Author: Igor `idle sign` Starikov
Author-email: idlesign@yandex.ru
License: BSD 3-Clause License
Platform: UNKNOWN
Classifier: Development Status :: 4 - Beta
Classifier: Operating System :: OS Independent
Classifier: Programming Language :: Python
Classifier: Programming Language :: Python :: 3
Classifier: Programming Language :: Python :: 3.6
Classifier: Programming Language :: Python :: 3.7
Classifier: Programming Language :: Python :: 3.8
Classifier: License :: OSI Approved :: BSD License
Provides-Extra: all
Requires-Dist: colorhash ; extra == 'all'
Requires-Dist: opencv-python ; extra == 'all'
